starhash/__init__.py
starhash/core.py
starhash/data/__init__.py
starhash/data/astronames_boost.txt
starhash/data/combolist.txt
starhash/data/eff_largewordlist.txt
starhash-1.0.2.dist-info/METADATA
starhash-1.0.2.dist-info/WHEEL
starhash-1.0.2.dist-info/entry_points.txt
starhash-1.0.2.dist-info/licenses/LICENSE
starhash-1.0.2.dist-info/RECORD
