Metadata-Version: 2.4
Name: starhash
Version: 1.0.2
Summary: Generate unique, memorable, and deterministic names for astronomical objects.
Project-URL: Homepage, https://github.com/tkillestein/starhash
Project-URL: Repository, https://github.com/tkillestein/starhash
Project-URL: Issues, https://github.com/tkillestein/starhash/issues
Author-email: Tom Killestein <tom.killestein@gmail.com>
Maintainer-email: Tom Killestein <tom.killestein@gmail.com>
License-Expression: MIT
License-File: LICENSE
Keywords: astronomy,coordinates,healpix,transients
Classifier: Development Status :: 4 - Beta
Classifier: Intended Audience :: Science/Research
Classifier: Programming Language :: Python :: 3
Classifier: Programming Language :: Python :: 3.11
Classifier: Programming Language :: Python :: 3.12
Classifier: Topic :: Scientific/Engineering :: Astronomy
Requires-Python: >=3.11
Requires-Dist: ff3>=1.0.2
Requires-Dist: healpy>=1.17.3
Requires-Dist: rich-click>=1.9.4
